quadpy/__init__.py
quadpy/_articles.py
quadpy/_common_citations.py
quadpy/_console.py
quadpy/_exception.py
quadpy/_optimize.py
quadpy/_scipy_compat.py
quadpy/cli.py
quadpy/py.typed
quadpy/c1/__init__.py
quadpy/c1/_adaptive.py
quadpy/c1/_chebyshev_gauss.py
quadpy/c1/_clenshaw_curtis.py
quadpy/c1/_fejer.py
quadpy/c1/_gauss_jacobi.py
quadpy/c1/_gauss_kronrod.py
quadpy/c1/_gauss_legendre.py
quadpy/c1/_gauss_lobatto.py
quadpy/c1/_gauss_patterson.py
quadpy/c1/_gauss_radau.py
quadpy/c1/_helpers.py
quadpy/c1/_midpoint.py
quadpy/c1/_newton_cotes.py
quadpy/c1/_trapezoidal.py
quadpy/c2/__init__.py
quadpy/c2/_albrecht_collatz.py
quadpy/c2/_burnside.py
quadpy/c2/_cohen_gismalla.py
quadpy/c2/_franke.py
quadpy/c2/_hammer_stroud.py
quadpy/c2/_helpers.py
quadpy/c2/_irwin.py
quadpy/c2/_maxwell.py
quadpy/c2/_meister.py
quadpy/c2/_miller.py
quadpy/c2/_phillips.py
quadpy/c2/_product.py
quadpy/c2/_stroud.py
quadpy/c2/_tyler.py
quadpy/c2/_waldron.py
quadpy/c2/_cools_haegemans_1985/__init__.py
quadpy/c2/_cools_haegemans_1985/c2_cools_haegemans_1985_09_1.json
quadpy/c2/_cools_haegemans_1985/c2_cools_haegemans_1985_13_1.json
quadpy/c2/_cools_haegemans_1985/c2_cools_haegemans_1985_13_2.json
quadpy/c2/_cools_haegemans_1985/c2_cools_haegemans_1985_13_3.json
quadpy/c2/_cools_haegemans_1985/c2_cools_haegemans_1985_17_1.json
quadpy/c2/_cools_haegemans_1985/c2_cools_haegemans_1985_17_2.json
quadpy/c2/_cools_haegemans_1988/__init__.py
quadpy/c2/_cools_haegemans_1988/c2_cools_haegemans_1988_1.json
quadpy/c2/_cools_haegemans_1988/c2_cools_haegemans_1988_2.json
quadpy/c2/_dunavant/__init__.py
quadpy/c2/_dunavant/c2_dunavant_04.json
quadpy/c2/_dunavant/c2_dunavant_05.json
quadpy/c2/_dunavant/c2_dunavant_06.json
quadpy/c2/_dunavant/c2_dunavant_07.json
quadpy/c2/_dunavant/c2_dunavant_08.json
quadpy/c2/_dunavant/c2_dunavant_09.json
quadpy/c2/_dunavant/c2_dunavant_10.json
quadpy/c2/_haegemans_piessens/__init__.py
quadpy/c2/_haegemans_piessens/c2_haegemans_piessens.json
quadpy-0.17.29.dist-info/METADATA
quadpy-0.17.29.dist-info/WHEEL
quadpy-0.17.29.dist-info/entry_points.txt
quadpy-0.17.29.dist-info/top_level.txt
quadpy-0.17.29.dist-info/RECORD
