Metadata-Version: 2.4
Name: quadpy
Version: 0.17.29
Summary: Numerical integration, quadrature for various domains
Author-email: Nico Schlömer <nico.schloemer@gmail.com>
License-Expression: LicenseRef-Proprietary
Project-URL: homepage, https://github.com/sigma-py/quadpy
Project-URL: issues, https://github.com/sigma-py/quadpy/issues
Project-URL:
Keywords:
Classifier: Development Status :: 5 - Production/Stable
Classifier: Intended Audience :: Science/Research
Classifier: Operating System :: OS Independent
Classifier: Programming Language :: Python
Classifier: Programming Language :: Python :: 3
Classifier: Programming Language :: Python :: 3.8
Classifier: Programming Language :: Python :: 3.9
Classifier: Programming Language :: Python :: 3.10
Classifier: Programming Language :: Python :: 3.11
Classifier: Programming Language :: Python :: 3.12
Classifier: Topic :: Scientific/Engineering
Classifier: Topic :: Scientific/Engineering :: Mathematics
Requires-Python: >=3.8
Requires-Dist: fjson
Requires-Dist: numpy>=1.20.0
Requires-Dist: stonefish-license-manager>=0.5.25
Requires-Dist: matplotlib
Requires-Dist: ndim>=0.1.23
Requires-Dist: orthopy<0.11,>=0.9.10
Requires-Dist: scipy
Requires-Dist: sympy
Provides-Extra: all
Requires-Dist: vtk; python_version < "3.12" and extra == "all"
Provides-Extra: plot
Requires-Dist: vtk; python_version < "3.12" and extra == "plot"
Requires-Dist: x22>=0.2.1
